pyreleaser/__init__.py
pyreleaser/cli.py
pyreleaser-0.5.2.dist-info/LICENSE.txt
pyreleaser-0.5.2.dist-info/METADATA
pyreleaser-0.5.2.dist-info/RECORD
pyreleaser-0.5.2.dist-info/WHEEL
pyreleaser-0.5.2.dist-info/entry_points.txt
pyreleaser-0.5.2.dist-info/top_level.txt
tests/__init__.py
tests/test_integration.py
