Metadata-Version: 2.1
Name: pyreleaser
Version: 0.5.2
Summary: Standard release flow for Python packages
Home-page: https://github.com/pior/pyreleaser
Author: Pior Bastida
Author-email: pior@pbastida.net
License: MIT
Keywords: release packaging twine setuptools
Platform: UNKNOWN
Classifier: Intended Audience :: Developers
Classifier: Programming Language :: Python
Classifier: Programming Language :: Python :: 3.6
Classifier: License :: OSI Approved :: MIT License
Requires-Dist: click
Requires-Dist: twine
